jvcprojector/__init__.py
jvcprojector/command.py
jvcprojector/connection.py
jvcprojector/const.py
jvcprojector/device.py
jvcprojector/error.py
jvcprojector/projector.py
jvcprojector/py.typed
pyjvcprojector_test-1.1.7.dist-info/licenses/LICENSE
pyjvcprojector_test-1.1.7.dist-info/METADATA
pyjvcprojector_test-1.1.7.dist-info/WHEEL
pyjvcprojector_test-1.1.7.dist-info/top_level.txt
pyjvcprojector_test-1.1.7.dist-info/RECORD
