Metadata-Version: 2.4
Name: pyjvcprojector_test
Version: 1.1.7
Summary: "A python library for controlling a JVC Projector over a network connection."
Home-page: https://github.com/iloveicedgreentea/pyjvcprojector
Author: iloveicedgreentea & Steve Easley
Classifier: Development Status :: 4 - Beta
Classifier: Intended Audience :: Developers
Classifier: License :: OSI Approved :: MIT License
Classifier: Topic :: Home Automation
Classifier: Topic :: Software Development :: Libraries
Classifier: Programming Language :: Python :: 3.10
License-File: LICENSE
Requires-Dist: aiodns>=3.2.0
Dynamic: license-file
